googleurlbuilder/__init__.py
googleurlbuilder/filters.py
googleurlbuilder/operators.py
googleurlbuilder/parameters.py
googleurlbuilder/tld.py
googleurlbuilder-0.1.0.dist-info/LICENSE
googleurlbuilder-0.1.0.dist-info/METADATA
googleurlbuilder-0.1.0.dist-info/WHEEL
googleurlbuilder-0.1.0.dist-info/top_level.txt
googleurlbuilder-0.1.0.dist-info/RECORD
