Metadata-Version: 2.1
Name: googleurlbuilder
Version: 0.1.0
Summary: Simple pure Python Google URL generator based on google(.com) advanced search.
Author: alexandrerbb
License: MIT License
Project-URL: Homepage, https://alexandrerbb.github.io/Google-URL-Builder/
Project-URL: Source, https://github.com/alexandrerbb/Google-URL-Builder
Keywords: google,url,generator,generate,link
Requires-Python: >=3.9
License-File: LICENSE
